{
    "sat mk clause 2ary": 1056,
    "sat mk clause 3ary": 467,
    "sat mk clause nary": 475,
    "sat mk var": 250,
    "sat del clause": 267,
    "sat conflicts": 321,
    "sat decisions": 617,
    "sat propagations 2ary": 12219,
    "sat propagations 3ary": 3606,
    "sat propagations nary": 2457,
    "sat restarts": 29,
    "sat minimized lits": 279,
    "sat subs resolution dyn": 71,
    "sat units": 35,
    "sat elim bool vars res": 33,
    "sat backjumps": 321,
    "sat elim clauses": 6,
    "sat elim literals": 19,
    "sat subsumed": 4,
    "sat scc elim binary": 210,
    "num allocs": 698797573,
    "rlimit count": 467632,
    "max memory": 20.15,
    "memory": 19.63,
    "time": 0.011,
    "build_time": 0.1775209903717041
}