{
    "sat mk clause 2ary": 129794,
    "sat mk clause 3ary": 324,
    "sat mk clause nary": 4382,
    "sat mk var": 2029,
    "sat del clause": 749,
    "sat conflicts": 2532,
    "sat decisions": 23871,
    "sat propagations 2ary": 774275,
    "sat propagations 3ary": 6474,
    "sat propagations nary": 70147,
    "sat restarts": 162,
    "sat minimized lits": 46456,
    "sat subs resolution dyn": 137269,
    "sat units": 67,
    "sat elim bool vars res": 625,
    "sat backjumps": 2532,
    "sat elim clauses": 176,
    "sat elim literals": 5457,
    "sat subsumed": 20,
    "sat subs resolution": 2042,
    "sat scc elim vars": 2,
    "sat scc elim binary": 2,
    "sat probing assigned": 58,
    "num allocs": 1595460337,
    "rlimit count": 13094194,
    "max memory": 83.42,
    "memory": 59.63,
    "time": 0.522,
    "build_time": 4.404797077178955
}